technopy/__init__.py
technopy/examples/hyperspectral.py
technopy/examples/virtual_reality.py
technopy/technoteam/activex.py
technopy/technoteam/camera.py
technopy/technoteam/capture.py
technopy/technoteam/coordinates.py
technopy/technoteam/evaluation.py
technopy/technoteam/image.py
technopy/technoteam/labsoft.py
technopy/technoteam/region.py
technopy/technoteam/table.py
technopy/technoteam/template_image_generator.py
technopy/useful/bob_the_builder.py
technopy/useful/fantasia.py
technopy/useful/postman_pat.py
technopy/variables/dicts.py
technopy-0.0.30.dist-info/LICENSE
technopy-0.0.30.dist-info/METADATA
technopy-0.0.30.dist-info/WHEEL
technopy-0.0.30.dist-info/top_level.txt
technopy-0.0.30.dist-info/RECORD
