Metadata-Version: 2.1
Name: technopy
Version: 0.0.30
Summary: technopy allows you to control your TechnoTeam Luminance Camera or Hyperspectral Camera.
Home-page: https://github.com/garethwalkom/technopy
Author: Gareth V. Walkom
Author-email: walkga04@googlemail.com
License: GPLv3
Keywords: TECHNOTEAM,METROLOGY,COLOR-SCIENCE,LIGHT,COLOR,LUMINANCE,HYSPERSPECTRAL,CAMERA,LIGHTING,HYPERSPECTRAL-IMAGING,IMAGE-PROCESSING
Platform: UNKNOWN
Classifier: Programming Language :: Python :: 3
Classifier: License :: OSI Approved :: GNU General Public License v3 (GPLv3)
Classifier: Operating System :: OS Independent
Requires-Python: >=3.6
Requires-Dist: luxpy (>=1.4.17)
Requires-Dist: matplotlib (>=3.1.3)
Requires-Dist: numpy (>=1.18.1)
Requires-Dist: pandas (>=1.0.1)
Requires-Dist: scikit-image (>=0.16.2)
